cg2at_lite/__init__.py
cg2at_lite/bin/__init__.py
cg2at_lite/bin/at_mod.py
cg2at_lite/bin/at_mod_np.py
cg2at_lite/bin/at_mod_p.py
cg2at_lite/bin/cg2at.py
cg2at_lite/bin/check_library.py
cg2at_lite/bin/g_var.py
cg2at_lite/bin/gen.py
cg2at_lite/bin/gro.py
cg2at_lite/bin/read_in.py
cg2at_lite/forcefields/README.md
cg2at_lite/forcefields/residuetypes.dat
cg2at_lite/forcefields/specbond.dat
cg2at_lite/forcefields/charmm36-ccd2md.ff/aminoacids.arn
cg2at_lite/forcefields/charmm36-ccd2md.ff/aminoacids.c.tdb
cg2at_lite/forcefields/charmm36-ccd2md.ff/aminoacids.hdb
cg2at_lite/forcefields/charmm36-ccd2md.ff/aminoacids.n.tdb
cg2at_lite/forcefields/charmm36-ccd2md.ff/aminoacids.r2b
cg2at_lite/forcefields/charmm36-ccd2md.ff/aminoacids.rtp
cg2at_lite/forcefields/charmm36-ccd2md.ff/atomtypes.atp
cg2at_lite/forcefields/charmm36-ccd2md.ff/carb.c.tdb
cg2at_lite/forcefields/charmm36-ccd2md.ff/carb.hdb
cg2at_lite/forcefields/charmm36-ccd2md.ff/carb.n.tdb
cg2at_lite/forcefields/charmm36-ccd2md.ff/carb.r2b
cg2at_lite/forcefields/charmm36-ccd2md.ff/carb.rtp
cg2at_lite/forcefields/charmm36-ccd2md.ff/cgenff.c.tdb
cg2at_lite/forcefields/charmm36-ccd2md.ff/cgenff.hdb
cg2at_lite/forcefields/charmm36-ccd2md.ff/cgenff.n.tdb
cg2at_lite/forcefields/charmm36-ccd2md.ff/cgenff.r2b
cg2at_lite/forcefields/charmm36-ccd2md.ff/cgenff.rtp
cg2at_lite/forcefields/charmm36-ccd2md.ff/cmap.itp
cg2at_lite/forcefields/charmm36-ccd2md.ff/ethers.hdb
cg2at_lite/forcefields/charmm36-ccd2md.ff/ethers.r2b
cg2at_lite/forcefields/charmm36-ccd2md.ff/ethers.rtp
cg2at_lite/forcefields/charmm36-ccd2md.ff/ffbonded.itp
cg2at_lite/forcefields/charmm36-ccd2md.ff/ffmissingdihedrals.itp
cg2at_lite/forcefields/charmm36-ccd2md.ff/ffnonbonded.itp
cg2at_lite/forcefields/charmm36-ccd2md.ff/forcefield.doc
cg2at_lite/forcefields/charmm36-ccd2md.ff/forcefield.itp
cg2at_lite/forcefields/charmm36-ccd2md.ff/ions.itp
cg2at_lite/forcefields/charmm36-ccd2md.ff/lip3.hdb~
cg2at_lite/forcefields/charmm36-ccd2md.ff/lipid.c.tdb
cg2at_lite-0.2.3.dist-info/licenses/LICENSE
cg2at_lite-0.2.3.dist-info/METADATA
cg2at_lite-0.2.3.dist-info/WHEEL
cg2at_lite-0.2.3.dist-info/entry_points.txt
cg2at_lite-0.2.3.dist-info/top_level.txt
cg2at_lite-0.2.3.dist-info/RECORD
