Metadata-Version: 2.4
Name: CG2AT-lite
Version: 0.2.3
Summary: A lite version of CG2AT for functionality with CCD2MD.
Author: Owen N. Vickery
Author-email: "Phillip J. Stansfeld" <phillip.stansfeld@warwick.ac.uk>
Maintainer-email: "Katarina E. Blow" <katarina.blow@warwick.ac.uk>, "Phillip J. Stansfeld" <phillip.stansfeld@warwick.ac.uk>
License-Expression: GPL-3.0
Project-URL: Homepage, https://github.com/pstansfeld/cg2at-lite
Project-URL: CG2AT, https://github.com/owenvickery/cg2at/
Keywords: CG,CCD2MD
Classifier: Programming Language :: Python :: 3
Requires-Python: >=3.7
License-File: LICENSE
Requires-Dist: numpy
Requires-Dist: scipy
Dynamic: license-file
